windowgpt/__init__.py
windowgpt/cli.py
windowgpt-0.1.9.dist-info/licenses/LICENSE
windowgpt-0.1.9.dist-info/METADATA
windowgpt-0.1.9.dist-info/WHEEL
windowgpt-0.1.9.dist-info/entry_points.txt
windowgpt-0.1.9.dist-info/top_level.txt
windowgpt-0.1.9.dist-info/RECORD
