Metadata-Version: 2.4
Name: windowgpt
Version: 0.1.9
Summary: Send a screenshot to ChatGPT Vision with a prompt
Home-page: https://github.com/yourusername/windowgpt
Author: Ed Atkinson
Author-email: ed.atkinson10@gmail.com
Requires-Python: >=3.7
License-File: LICENSE
Requires-Dist: pyautogui
Requires-Dist: pillow
Requires-Dist: openai
Dynamic: author
Dynamic: author-email
Dynamic: home-page
Dynamic: license-file
Dynamic: requires-dist
Dynamic: requires-python
Dynamic: summary
